[
  {
    "_metadata": {
      "extracted_at": "2025-10-26T05:20:50.238268",
      "file_path": "data/silver/user_collaboration_metrics.json",
      "record_count": 18
    }
  },
  {
    "user": "danrleypereira",
    "collaborator_count": 17,
    "collaborators": [
      "polyanacunha",
      "Gabriel-br07",
      "Lucas-Germano",
      "tauisilva",
      "whiterabbitholes",
      "juanpbarros20",
      "thiagodiasz",
      "pedruck",
      "GuiMcs00",
      "YuriNoriki",
      "araujow-g",
      "Bnicole98",
      "Danilo019",
      "MartinsArtur",
      "josue-oliveiraa",
      "leltonborges",
      "Bappoz"
    ],
    "repositories_contributed": 5
  },
  {
    "user": "GuiMcs00",
    "collaborator_count": 14,
    "collaborators": [
      "polyanacunha",
      "Gabriel-br07",
      "Lucas-Germano",
      "whiterabbitholes",
      "juanpbarros20",
      "thiagodiasz",
      "pedruck",
      "danrleypereira",
      "YuriNoriki",
      "araujow-g",
      "Bnicole98",
      "Danilo019",
      "josue-oliveiraa",
      "Bappoz"
    ],
    "repositories_contributed": 3
  },
  {
    "user": "Gabriel-br07",
    "collaborator_count": 12,
    "collaborators": [
      "polyanacunha",
      "Lucas-Germano",
      "thiagodiasz",
      "danrleypereira",
      "pedruck",
      "GuiMcs00",
      "araujow-g",
      "YuriNoriki",
      "Bnicole98",
      "Danilo019",
      "josue-oliveiraa",
      "Bappoz"
    ],
    "repositories_contributed": 2
  },
  {
    "user": "josue-oliveiraa",
    "collaborator_count": 12,
    "collaborators": [
      "polyanacunha",
      "Gabriel-br07",
      "Lucas-Germano",
      "thiagodiasz",
      "GuiMcs00",
      "pedruck",
      "danrleypereira",
      "araujow-g",
      "YuriNoriki",
      "Bnicole98",
      "Danilo019",
      "Bappoz"
    ],
    "repositories_contributed": 2
  },
  {
    "user": "Lucas-Germano",
    "collaborator_count": 8,
    "collaborators": [
      "Gabriel-br07",
      "thiagodiasz",
      "danrleypereira",
      "Bnicole98",
      "GuiMcs00",
      "Danilo019",
      "josue-oliveiraa",
      "Bappoz"
    ],
    "repositories_contributed": 1
  },
  {
    "user": "thiagodiasz",
    "collaborator_count": 8,
    "collaborators": [
      "Lucas-Germano",
      "Gabriel-br07",
      "GuiMcs00",
      "Bnicole98",
      "danrleypereira",
      "Danilo019",
      "josue-oliveiraa",
      "Bappoz"
    ],
    "repositories_contributed": 1
  },
  {
    "user": "Bnicole98",
    "collaborator_count": 8,
    "collaborators": [
      "Lucas-Germano",
      "Gabriel-br07",
      "thiagodiasz",
      "GuiMcs00",
      "danrleypereira",
      "Danilo019",
      "josue-oliveiraa",
      "Bappoz"
    ],
    "repositories_contributed": 1
  },
  {
    "user": "Danilo019",
    "collaborator_count": 8,
    "collaborators": [
      "Lucas-Germano",
      "Gabriel-br07",
      "thiagodiasz",
      "GuiMcs00",
      "danrleypereira",
      "Bnicole98",
      "josue-oliveiraa",
      "Bappoz"
    ],
    "repositories_contributed": 1
  },
  {
    "user": "Bappoz",
    "collaborator_count": 8,
    "collaborators": [
      "Lucas-Germano",
      "Gabriel-br07",
      "thiagodiasz",
      "GuiMcs00",
      "danrleypereira",
      "Bnicole98",
      "Danilo019",
      "josue-oliveiraa"
    ],
    "repositories_contributed": 1
  },
  {
    "user": "polyanacunha",
    "collaborator_count": 7,
    "collaborators": [
      "Gabriel-br07",
      "danrleypereira",
      "pedruck",
      "GuiMcs00",
      "araujow-g",
      "YuriNoriki",
      "josue-oliveiraa"
    ],
    "repositories_contributed": 1
  },
  {
    "user": "pedruck",
    "collaborator_count": 7,
    "collaborators": [
      "polyanacunha",
      "Gabriel-br07",
      "GuiMcs00",
      "danrleypereira",
      "YuriNoriki",
      "araujow-g",
      "josue-oliveiraa"
    ],
    "repositories_contributed": 1
  },
  {
    "user": "araujow-g",
    "collaborator_count": 7,
    "collaborators": [
      "polyanacunha",
      "Gabriel-br07",
      "GuiMcs00",
      "pedruck",
      "danrleypereira",
      "YuriNoriki",
      "josue-oliveiraa"
    ],
    "repositories_contributed": 1
  },
  {
    "user": "YuriNoriki",
    "collaborator_count": 7,
    "collaborators": [
      "polyanacunha",
      "Gabriel-br07",
      "GuiMcs00",
      "pedruck",
      "danrleypereira",
      "araujow-g",
      "josue-oliveiraa"
    ],
    "repositories_contributed": 1
  },
  {
    "user": "tauisilva",
    "collaborator_count": 3,
    "collaborators": [
      "danrleypereira",
      "MartinsArtur",
      "leltonborges"
    ],
    "repositories_contributed": 1
  },
  {
    "user": "MartinsArtur",
    "collaborator_count": 3,
    "collaborators": [
      "tauisilva",
      "danrleypereira",
      "leltonborges"
    ],
    "repositories_contributed": 1
  },
  {
    "user": "leltonborges",
    "collaborator_count": 3,
    "collaborators": [
      "tauisilva",
      "danrleypereira",
      "MartinsArtur"
    ],
    "repositories_contributed": 1
  },
  {
    "user": "whiterabbitholes",
    "collaborator_count": 3,
    "collaborators": [
      "danrleypereira",
      "juanpbarros20",
      "GuiMcs00"
    ],
    "repositories_contributed": 1
  },
  {
    "user": "juanpbarros20",
    "collaborator_count": 3,
    "collaborators": [
      "danrleypereira",
      "whiterabbitholes",
      "GuiMcs00"
    ],
    "repositories_contributed": 1
  }
]